{
  "id": "map_winding_path",
  "name": "The Winding Path",
  "width": 80,
  "height": 80,
  "readyToUse": true,
  "tiles": {
    "2,2": "SPAWN_POINT",
    "4,4": "SPAWN_POINT",
    "2,6": "SPAWN_POINT",
    "77,77": "TARGET",
    "26,21": "PATH",
    "67,59": "PATH",
    "78,59": "PATH",
    "15,21": "PATH",
    "78,68": "PATH",
    "78,77": "PATH",
    "48,45": "PATH",
    "11,5": "PATH",
    "40,41": "PATH",
    "48,54": "PATH",
    "30,18": "PATH",
    "11,14": "PATH",
    "48,63": "PATH",
    "41,24": "PATH",
    "41,33": "PATH",
    "74,57": "PATH",
    "37,17": "PATH",
    "51,64": "PATH",
    "7,3": "PATH",
    "55,61": "PATH",
    "78,63": "PATH",
    "59,59": "PATH",
    "70,59": "PATH",
    "78,72": "PATH",
    "18,21": "PATH",
    "40,27": "PATH",
    "8,4": "PATH",
    "48,40": "PATH",
    "77,76": "PATH",
    "40,36": "PATH",
    "48,49": "PATH",
    "11,9": "PATH",
    "48,58": "PATH",
    "41,19": "PATH",
    "33,15": "PATH",
    "41,28": "PATH",
    "41,37": "PATH",
    "25,20": "PATH",
    "34,16": "PATH",
    "22,23": "PATH",
    "66,57": "PATH",
    "26,20": "PATH",
    "67,58": "PATH",
    "78,58": "PATH",
    "40,22": "PATH",
    "77,71": "PATH",
    "40,31": "PATH",
    "48,44": "PATH",
    "11,4": "PATH",
    "40,40": "PATH",
    "48,53": "PATH",
    "41,23": "PATH",
    "41,32": "PATH",
    "3,5": "PATH",
    "43,41": "PATH",
    "37,16": "PATH",
    "51,63": "PATH",
    "14,23": "PATH",
    "55,60": "PATH",
    "77,57": "PATH",
    "29,17": "PATH",
    "40,17": "PATH",
    "77,66": "PATH",
    "40,26": "PATH",
    "77,75": "PATH",
    "21,22": "PATH",
    "48,39": "PATH",
    "40,35": "PATH",
    "50,58": "PATH",
    "50,67": "PATH",
    "10,3": "PATH",
    "41,18": "PATH",
    "62,59": "PATH",
    "73,59": "PATH",
    "54,64": "PATH",
    "51,67": "PATH",
    "36,15": "PATH",
    "28,20": "PATH",
    "76,69": "PATH",
    "77,61": "PATH",
    "40,21": "PATH",
    "69,57": "PATH",
    "77,70": "PATH",
    "50,53": "PATH",
    "40,30": "PATH",
    "50,62": "PATH",
    "3,4": "PATH",
    "43,40": "PATH",
    "76,64": "PATH",
    "57,60": "PATH",
    "76,73": "PATH",
    "49,65": "PATH",
    "6,5": "PATH",
    "40,16": "PATH",
    "29,16": "PATH",
    "77,65": "PATH",
    "50,48": "PATH",
    "40,25": "PATH",
    "77,74": "PATH",
    "50,57": "PATH",
    "61,57": "PATH",
    "21,21": "PATH",
    "50,66": "PATH",
    "39,29": "PATH",
    "39,38": "PATH",
    "62,58": "PATH",
    "73,58": "PATH",
    "32,17": "PATH",
    "13,13": "PATH",
    "54,63": "PATH",
    "13,22": "PATH",
    "24,22": "PATH",
    "65,59": "PATH",
    "76,59": "PATH",
    "28,19": "PATH",
    "76,68": "PATH",
    "49,51": "PATH",
    "76,77": "PATH",
    "49,60": "PATH",
    "77,60": "PATH",
    "50,43": "PATH",
    "42,39": "PATH",
    "50,52": "PATH",
    "50,61": "PATH",
    "39,24": "PATH",
    "39,33": "PATH",
    "13,8": "PATH",
    "72,57": "PATH",
    "35,17": "PATH",
    "13,17": "PATH",
    "53,62": "PATH",
    "43,39": "PATH",
    "16,22": "PATH",
    "46,41": "PATH",
    "5,3": "PATH",
    "76,63": "PATH",
    "49,46": "PATH",
    "57,59": "PATH",
    "68,59": "PATH",
    "17,23": "PATH",
    "49,55": "PATH",
    "76,72": "PATH",
    "49,64": "PATH",
    "6,4": "PATH",
    "50,47": "PATH",
    "50,56": "PATH",
    "39,19": "PATH",
    "31,15": "PATH",
    "39,28": "PATH",
    "39,37": "PATH",
    "12,20": "PATH",
    "75,58": "PATH",
    "32,16": "PATH",
    "13,12": "PATH",
    "13,21": "PATH",
    "64,57": "PATH",
    "24,21": "PATH",
    "56,62": "PATH",
    "65,58": "PATH",
    "49,41": "PATH",
    "76,58": "PATH",
    "28,18": "PATH",
    "9,5": "PATH",
    "76,67": "PATH",
    "49,50": "PATH",
    "49,59": "PATH",
    "49,68": "PATH",
    "50,42": "PATH",
    "50,51": "PATH",
    "39,23": "PATH",
    "12,6": "PATH",
    "39,32": "PATH",
    "12,15": "PATH",
    "13,7": "PATH",
    "45,39": "PATH",
    "35,16": "PATH",
    "13,16": "PATH",
    "53,61": "PATH",
    "16,21": "PATH",
    "46,40": "PATH",
    "49,45": "PATH",
    "68,58": "PATH",
    "57,58": "PATH",
    "49,54": "PATH",
    "49,63": "PATH",
    "19,22": "PATH",
    "11,18": "PATH",
    "48,67": "PATH",
    "39,18": "PATH",
    "39,27": "PATH",
    "12,10": "PATH",
    "20,23": "PATH",
    "60,59": "PATH",
    "12,19": "PATH",
    "75,57": "PATH",
    "52,64": "PATH",
    "13,11": "PATH",
    "53,65": "PATH",
    "56,61": "PATH",
    "78,67": "PATH",
    "49,40": "PATH",
    "78,76": "PATH",
    "49,49": "PATH",
    "27,21": "PATH",
    "30,17": "PATH",
    "11,13": "PATH",
    "48,62": "PATH",
    "39,22": "PATH",
    "12,5": "PATH",
    "41,41": "PATH",
    "12,14": "PATH",
    "23,23": "PATH",
    "38,17": "PATH",
    "78,62": "PATH",
    "46,39": "PATH",
    "59,58": "PATH",
    "70,58": "PATH",
    "78,71": "PATH",
    "49,44": "PATH",
    "8,3": "PATH",
    "48,48": "PATH",
    "11,8": "PATH",
    "71,59": "PATH",
    "48,57": "PATH",
    "19,21": "PATH",
    "11,17": "PATH",
    "48,66": "PATH",
    "41,27": "PATH",
    "41,36": "PATH",
    "12,9": "PATH",
    "60,58": "PATH",
    "44,41": "PATH",
    "4,5": "PATH",
    "34,15": "PATH",
    "52,63": "PATH",
    "22,22": "PATH",
    "67,57": "PATH",
    "26,19": "PATH",
    "78,66": "PATH",
    "78,75": "PATH",
    "48,43": "PATH",
    "27,20": "PATH",
    "40,39": "PATH",
    "11,3": "PATH",
    "30,16": "PATH",
    "48,52": "PATH",
    "11,12": "PATH",
    "48,61": "PATH",
    "63,59": "PATH",
    "41,22": "PATH",
    "11,21": "PATH",
    "41,31": "PATH",
    "12,4": "PATH",
    "41,40": "PATH",
    "25,23": "PATH",
    "37,15": "PATH",
    "14,22": "PATH",
    "38,16": "PATH",
    "55,59": "PATH",
    "78,61": "PATH",
    "15,23": "PATH",
    "59,57": "PATH",
    "70,57": "PATH",
    "78,70": "PATH",
    "40,34": "PATH",
    "48,47": "PATH",
    "11,7": "PATH",
    "71,58": "PATH",
    "48,56": "PATH",
    "11,16": "PATH",
    "41,17": "PATH",
    "48,65": "PATH",
    "41,26": "PATH",
    "41,35": "PATH",
    "44,40": "PATH",
    "74,59": "PATH",
    "22,21": "PATH",
    "51,66": "PATH",
    "7,5": "PATH",
    "47,41": "PATH",
    "67,56": "PATH",
    "78,65": "PATH",
    "55,63": "PATH",
    "18,23": "PATH",
    "40,20": "PATH",
    "77,69": "PATH",
    "40,29": "PATH",
    "48,42": "PATH",
    "40,38": "PATH",
    "48,51": "PATH",
    "41,21": "PATH",
    "33,17": "PATH",
    "41,30": "PATH",
    "41,39": "PATH",
    "25,22": "PATH",
    "14,21": "PATH",
    "66,59": "PATH",
    "40,15": "PATH",
    "77,64": "PATH",
    "58,60": "PATH",
    "40,24": "PATH",
    "77,73": "PATH",
    "40,33": "PATH",
    "48,46": "PATH",
    "50,65": "PATH",
    "41,16": "PATH",
    "41,25": "PATH",
    "62,57": "PATH",
    "73,57": "PATH",
    "54,62": "PATH",
    "74,58": "PATH",
    "51,65": "PATH",
    "7,4": "PATH",
    "47,40": "PATH",
    "76,76": "PATH",
    "77,59": "PATH",
    "40,19": "PATH",
    "29,19": "PATH",
    "77,68": "PATH",
    "40,28": "PATH",
    "50,60": "PATH",
    "40,37": "PATH",
    "10,5": "PATH",
    "41,20": "PATH",
    "33,16": "PATH",
    "25,21": "PATH",
    "66,58": "PATH",
    "36,17": "PATH",
    "76,62": "PATH",
    "17,22": "PATH",
    "76,71": "PATH",
    "6,3": "PATH",
    "77,63": "PATH",
    "50,46": "PATH",
    "58,59": "PATH",
    "69,59": "PATH",
    "40,23": "PATH",
    "77,72": "PATH",
    "50,55": "PATH",
    "40,32": "PATH",
    "50,64": "PATH",
    "39,36": "PATH",
    "32,15": "PATH",
    "54,61": "PATH",
    "13,20": "PATH",
    "65,57": "PATH",
    "9,4": "PATH",
    "76,57": "PATH",
    "28,17": "PATH",
    "76,66": "PATH",
    "76,75": "PATH",
    "49,58": "PATH",
    "47,39": "PATH",
    "49,67": "PATH",
    "77,58": "PATH",
    "50,41": "PATH",
    "29,18": "PATH",
    "40,18": "PATH",
    "77,67": "PATH",
    "50,50": "PATH",
    "61,59": "PATH",
    "50,59": "PATH",
    "21,23": "PATH",
    "50,68": "PATH",
    "39,31": "PATH",
    "10,4": "PATH",
    "39,40": "PATH",
    "13,6": "PATH",
    "35,15": "PATH",
    "13,15": "PATH",
    "36,16": "PATH",
    "76,61": "PATH",
    "68,57": "PATH",
    "17,21": "PATH",
    "76,70": "PATH",
    "49,53": "PATH",
    "49,62": "PATH",
    "77,62": "PATH",
    "50,45": "PATH",
    "58,58": "PATH",
    "69,58": "PATH",
    "42,41": "PATH",
    "50,54": "PATH",
    "39,17": "PATH",
    "50,63": "PATH",
    "39,26": "PATH",
    "20,22": "PATH",
    "39,35": "PATH",
    "12,18": "PATH",
    "2,4": "PATH",
    "13,10": "PATH",
    "72,59": "PATH",
    "13,19": "PATH",
    "53,64": "PATH",
    "56,60": "PATH",
    "5,5": "PATH",
    "49,39": "PATH",
    "9,3": "PATH",
    "76,65": "PATH",
    "49,48": "PATH",
    "57,61": "PATH",
    "76,74": "PATH",
    "49,57": "PATH",
    "49,66": "PATH",
    "50,40": "PATH",
    "50,49": "PATH",
    "61,58": "PATH",
    "39,21": "PATH",
    "31,17": "PATH",
    "39,30": "PATH",
    "12,13": "PATH",
    "39,39": "PATH",
    "23,22": "PATH",
    "12,22": "PATH",
    "13,5": "PATH",
    "13,14": "PATH",
    "64,59": "PATH",
    "13,23": "PATH",
    "24,23": "PATH",
    "76,60": "PATH",
    "49,43": "PATH",
    "68,56": "PATH",
    "49,52": "PATH",
    "49,61": "PATH",
    "50,44": "PATH",
    "42,40": "PATH",
    "39,16": "PATH",
    "39,25": "PATH",
    "12,8": "PATH",
    "20,21": "PATH",
    "39,34": "PATH",
    "12,17": "PATH",
    "60,57": "PATH",
    "13,9": "PATH",
    "72,58": "PATH",
    "45,41": "PATH",
    "13,18": "PATH",
    "53,63": "PATH",
    "16,23": "PATH",
    "56,59": "PATH",
    "5,4": "PATH",
    "78,74": "PATH",
    "49,47": "PATH",
    "49,56": "PATH",
    "27,19": "PATH",
    "30,15": "PATH",
    "11,11": "PATH",
    "48,60": "PATH",
    "63,58": "PATH",
    "11,20": "PATH",
    "39,20": "PATH",
    "12,3": "PATH",
    "31,16": "PATH",
    "12,12": "PATH",
    "12,21": "PATH",
    "75,59": "PATH",
    "23,21": "PATH",
    "52,66": "PATH",
    "13,4": "PATH",
    "64,58": "PATH",
    "38,15": "PATH",
    "26,22": "PATH",
    "15,22": "PATH",
    "78,60": "PATH",
    "78,69": "PATH",
    "49,42": "PATH",
    "11,6": "PATH",
    "71,57": "PATH",
    "48,55": "PATH",
    "11,15": "PATH",
    "48,64": "PATH",
    "39,15": "PATH",
    "41,34": "PATH",
    "12,7": "PATH",
    "44,39": "PATH",
    "4,3": "PATH",
    "12,16": "PATH",
    "45,40": "PATH",
    "78,64": "PATH",
    "55,62": "PATH",
    "18,22": "PATH",
    "78,73": "PATH",
    "8,5": "PATH",
    "48,41": "PATH",
    "27,18": "PATH",
    "48,50": "PATH",
    "11,10": "PATH",
    "48,59": "PATH",
    "19,23": "PATH",
    "11,19": "PATH",
    "63,57": "PATH",
    "41,29": "PATH",
    "41,38": "PATH",
    "12,11": "PATH",
    "34,17": "PATH",
    "52,65": "PATH",
    "1,3": "BUILD_AREA",
    "1,4": "BUILD_AREA",
    "1,5": "BUILD_AREA",
    "2,3": "BUILD_AREA",
    "2,5": "BUILD_AREA",
    "3,3": "BUILD_AREA",
    "3,6": "BUILD_AREA",
    "4,2": "BUILD_AREA",
    "4,6": "BUILD_AREA",
    "5,2": "BUILD_AREA",
    "5,6": "BUILD_AREA",
    "6,2": "BUILD_AREA",
    "6,6": "BUILD_AREA",
    "7,2": "BUILD_AREA",
    "7,6": "BUILD_AREA",
    "8,2": "BUILD_AREA",
    "8,6": "BUILD_AREA",
    "9,2": "BUILD_AREA",
    "9,6": "BUILD_AREA",
    "10,2": "BUILD_AREA",
    "10,6": "BUILD_AREA",
    "10,7": "BUILD_AREA",
    "10,8": "BUILD_AREA",
    "10,9": "BUILD_AREA",
    "10,10": "BUILD_AREA",
    "10,11": "BUILD_AREA",
    "10,12": "BUILD_AREA",
    "10,13": "BUILD_AREA",
    "10,14": "BUILD_AREA",
    "10,15": "BUILD_AREA",
    "10,16": "BUILD_AREA",
    "10,17": "BUILD_AREA",
    "10,18": "BUILD_AREA",
    "10,19": "BUILD_AREA",
    "10,20": "BUILD_AREA",
    "10,21": "BUILD_AREA",
    "11,2": "BUILD_AREA",
    "11,22": "BUILD_AREA",
    "11,23": "BUILD_AREA",
    "12,2": "BUILD_AREA",
    "12,23": "BUILD_AREA",
    "13,2": "BUILD_AREA",
    "13,3": "BUILD_AREA",
    "13,24": "BUILD_AREA",
    "14,4": "BUILD_AREA",
    "14,5": "BUILD_AREA",
    "14,6": "BUILD_AREA",
    "14,7": "BUILD_AREA",
    "14,8": "BUILD_AREA",
    "14,9": "BUILD_AREA",
    "14,10": "BUILD_AREA",
    "14,11": "BUILD_AREA",
    "14,12": "BUILD_AREA",
    "14,13": "BUILD_AREA",
    "14,14": "BUILD_AREA",
    "14,15": "BUILD_AREA",
    "14,16": "BUILD_AREA",
    "14,17": "BUILD_AREA",
    "14,18": "BUILD_AREA",
    "14,19": "BUILD_AREA",
    "14,20": "BUILD_AREA",
    "14,24": "BUILD_AREA",
    "15,20": "BUILD_AREA",
    "15,24": "BUILD_AREA",
    "16,20": "BUILD_AREA",
    "16,24": "BUILD_AREA",
    "17,20": "BUILD_AREA",
    "17,24": "BUILD_AREA",
    "18,20": "BUILD_AREA",
    "18,24": "BUILD_AREA",
    "19,20": "BUILD_AREA",
    "19,24": "BUILD_AREA",
    "20,20": "BUILD_AREA",
    "20,24": "BUILD_AREA",
    "21,20": "BUILD_AREA",
    "21,24": "BUILD_AREA",
    "22,20": "BUILD_AREA",
    "22,24": "BUILD_AREA",
    "23,20": "BUILD_AREA",
    "23,24": "BUILD_AREA",
    "24,19": "BUILD_AREA",
    "24,20": "BUILD_AREA",
    "24,24": "BUILD_AREA",
    "25,19": "BUILD_AREA",
    "25,24": "BUILD_AREA",
    "26,17": "BUILD_AREA",
    "26,18": "BUILD_AREA",
    "26,23": "BUILD_AREA",
    "26,24": "BUILD_AREA",
    "27,17": "BUILD_AREA",
    "27,22": "BUILD_AREA",
    "28,15": "BUILD_AREA",
    "28,16": "BUILD_AREA",
    "28,21": "BUILD_AREA",
    "28,22": "BUILD_AREA",
    "29,15": "BUILD_AREA",
    "29,20": "BUILD_AREA",
    "30,14": "BUILD_AREA",
    "30,19": "BUILD_AREA",
    "30,20": "BUILD_AREA",
    "31,14": "BUILD_AREA",
    "31,18": "BUILD_AREA",
    "32,14": "BUILD_AREA",
    "32,18": "BUILD_AREA",
    "33,14": "BUILD_AREA",
    "33,18": "BUILD_AREA",
    "34,14": "BUILD_AREA",
    "34,18": "BUILD_AREA",
    "35,14": "BUILD_AREA",
    "35,18": "BUILD_AREA",
    "36,14": "BUILD_AREA",
    "36,18": "BUILD_AREA",
    "37,14": "BUILD_AREA",
    "37,18": "BUILD_AREA",
    "38,14": "BUILD_AREA",
    "38,18": "BUILD_AREA",
    "38,19": "BUILD_AREA",
    "38,20": "BUILD_AREA",
    "38,21": "BUILD_AREA",
    "38,22": "BUILD_AREA",
    "38,23": "BUILD_AREA",
    "38,24": "BUILD_AREA",
    "38,25": "BUILD_AREA",
    "38,26": "BUILD_AREA",
    "38,27": "BUILD_AREA",
    "38,28": "BUILD_AREA",
    "38,29": "BUILD_AREA",
    "38,30": "BUILD_AREA",
    "38,31": "BUILD_AREA",
    "38,32": "BUILD_AREA",
    "38,33": "BUILD_AREA",
    "38,34": "BUILD_AREA",
    "38,35": "BUILD_AREA",
    "38,36": "BUILD_AREA",
    "38,37": "BUILD_AREA",
    "38,38": "BUILD_AREA",
    "38,39": "BUILD_AREA",
    "38,40": "BUILD_AREA",
    "38,41": "BUILD_AREA",
    "39,14": "BUILD_AREA",
    "39,41": "BUILD_AREA",
    "40,14": "BUILD_AREA",
    "40,42": "BUILD_AREA",
    "41,14": "BUILD_AREA",
    "41,15": "BUILD_AREA",
    "41,42": "BUILD_AREA",
    "42,16": "BUILD_AREA",
    "42,17": "BUILD_AREA",
    "42,18": "BUILD_AREA",
    "42,19": "BUILD_AREA",
    "42,20": "BUILD_AREA",
    "42,21": "BUILD_AREA",
    "42,22": "BUILD_AREA",
    "42,23": "BUILD_AREA",
    "42,24": "BUILD_AREA",
    "42,25": "BUILD_AREA",
    "42,26": "BUILD_AREA",
    "42,27": "BUILD_AREA",
    "42,28": "BUILD_AREA",
    "42,29": "BUILD_AREA",
    "42,30": "BUILD_AREA",
    "42,31": "BUILD_AREA",
    "42,32": "BUILD_AREA",
    "42,33": "BUILD_AREA",
    "42,34": "BUILD_AREA",
    "42,35": "BUILD_AREA",
    "42,36": "BUILD_AREA",
    "42,37": "BUILD_AREA",
    "42,38": "BUILD_AREA",
    "42,42": "BUILD_AREA",
    "43,38": "BUILD_AREA",
    "43,42": "BUILD_AREA",
    "44,38": "BUILD_AREA",
    "44,42": "BUILD_AREA",
    "45,38": "BUILD_AREA",
    "45,42": "BUILD_AREA",
    "46,38": "BUILD_AREA",
    "46,42": "BUILD_AREA",
    "47,38": "BUILD_AREA",
    "47,42": "BUILD_AREA",
    "47,43": "BUILD_AREA",
    "47,44": "BUILD_AREA",
    "47,45": "BUILD_AREA",
    "47,46": "BUILD_AREA",
    "47,47": "BUILD_AREA",
    "47,48": "BUILD_AREA",
    "47,49": "BUILD_AREA",
    "47,50": "BUILD_AREA",
    "47,51": "BUILD_AREA",
    "47,52": "BUILD_AREA",
    "47,53": "BUILD_AREA",
    "47,54": "BUILD_AREA",
    "47,55": "BUILD_AREA",
    "47,56": "BUILD_AREA",
    "47,57": "BUILD_AREA",
    "47,58": "BUILD_AREA",
    "47,59": "BUILD_AREA",
    "47,60": "BUILD_AREA",
    "47,61": "BUILD_AREA",
    "47,62": "BUILD_AREA",
    "47,63": "BUILD_AREA",
    "47,64": "BUILD_AREA",
    "47,65": "BUILD_AREA",
    "47,66": "BUILD_AREA",
    "47,67": "BUILD_AREA",
    "48,38": "BUILD_AREA",
    "48,68": "BUILD_AREA",
    "48,69": "BUILD_AREA",
    "49,38": "BUILD_AREA",
    "49,69": "BUILD_AREA",
    "50,38": "BUILD_AREA",
    "50,39": "BUILD_AREA",
    "50,69": "BUILD_AREA",
    "51,40": "BUILD_AREA",
    "51,41": "BUILD_AREA",
    "51,42": "BUILD_AREA",
    "51,43": "BUILD_AREA",
    "51,44": "BUILD_AREA",
    "51,45": "BUILD_AREA",
    "51,46": "BUILD_AREA",
    "51,47": "BUILD_AREA",
    "51,48": "BUILD_AREA",
    "51,49": "BUILD_AREA",
    "51,50": "BUILD_AREA",
    "51,51": "BUILD_AREA",
    "51,52": "BUILD_AREA",
    "51,53": "BUILD_AREA",
    "51,54": "BUILD_AREA",
    "51,55": "BUILD_AREA",
    "51,56": "BUILD_AREA",
    "51,57": "BUILD_AREA",
    "51,58": "BUILD_AREA",
    "51,59": "BUILD_AREA",
    "51,60": "BUILD_AREA",
    "51,61": "BUILD_AREA",
    "51,62": "BUILD_AREA",
    "51,68": "BUILD_AREA",
    "52,61": "BUILD_AREA",
    "52,62": "BUILD_AREA",
    "52,67": "BUILD_AREA",
    "52,68": "BUILD_AREA",
    "53,60": "BUILD_AREA",
    "53,66": "BUILD_AREA",
    "54,59": "BUILD_AREA",
    "54,60": "BUILD_AREA",
    "54,65": "BUILD_AREA",
    "54,66": "BUILD_AREA",
    "55,58": "BUILD_AREA",
    "55,64": "BUILD_AREA",
    "56,57": "BUILD_AREA",
    "56,58": "BUILD_AREA",
    "56,63": "BUILD_AREA",
    "56,64": "BUILD_AREA",
    "57,57": "BUILD_AREA",
    "57,62": "BUILD_AREA",
    "58,57": "BUILD_AREA",
    "58,61": "BUILD_AREA",
    "58,62": "BUILD_AREA",
    "59,56": "BUILD_AREA",
    "59,60": "BUILD_AREA",
    "60,56": "BUILD_AREA",
    "60,60": "BUILD_AREA",
    "61,56": "BUILD_AREA",
    "61,60": "BUILD_AREA",
    "62,56": "BUILD_AREA",
    "62,60": "BUILD_AREA",
    "63,56": "BUILD_AREA",
    "63,60": "BUILD_AREA",
    "64,56": "BUILD_AREA",
    "64,60": "BUILD_AREA",
    "65,56": "BUILD_AREA",
    "65,60": "BUILD_AREA",
    "66,55": "BUILD_AREA",
    "66,56": "BUILD_AREA",
    "66,60": "BUILD_AREA",
    "67,55": "BUILD_AREA",
    "67,60": "BUILD_AREA",
    "68,55": "BUILD_AREA",
    "68,60": "BUILD_AREA",
    "69,56": "BUILD_AREA",
    "69,60": "BUILD_AREA",
    "70,56": "BUILD_AREA",
    "70,60": "BUILD_AREA",
    "71,56": "BUILD_AREA",
    "71,60": "BUILD_AREA",
    "72,56": "BUILD_AREA",
    "72,60": "BUILD_AREA",
    "73,56": "BUILD_AREA",
    "73,60": "BUILD_AREA",
    "74,56": "BUILD_AREA",
    "74,60": "BUILD_AREA",
    "75,56": "BUILD_AREA",
    "75,60": "BUILD_AREA",
    "75,61": "BUILD_AREA",
    "75,62": "BUILD_AREA",
    "75,63": "BUILD_AREA",
    "75,64": "BUILD_AREA",
    "75,65": "BUILD_AREA",
    "75,66": "BUILD_AREA",
    "75,67": "BUILD_AREA",
    "75,68": "BUILD_AREA",
    "75,69": "BUILD_AREA",
    "75,70": "BUILD_AREA",
    "75,71": "BUILD_AREA",
    "75,72": "BUILD_AREA",
    "75,73": "BUILD_AREA",
    "75,74": "BUILD_AREA",
    "75,75": "BUILD_AREA",
    "75,76": "BUILD_AREA",
    "75,77": "BUILD_AREA",
    "76,56": "BUILD_AREA",
    "76,78": "BUILD_AREA",
    "77,56": "BUILD_AREA",
    "77,78": "BUILD_AREA",
    "78,56": "BUILD_AREA",
    "78,57": "BUILD_AREA",
    "78,78": "BUILD_AREA",
    "79,58": "BUILD_AREA",
    "79,59": "BUILD_AREA",
    "79,60": "BUILD_AREA",
    "79,61": "BUILD_AREA",
    "79,62": "BUILD_AREA",
    "79,63": "BUILD_AREA",
    "79,64": "BUILD_AREA",
    "79,65": "BUILD_AREA",
    "79,66": "BUILD_AREA",
    "79,67": "BUILD_AREA",
    "79,68": "BUILD_AREA",
    "79,69": "BUILD_AREA",
    "79,70": "BUILD_AREA",
    "79,71": "BUILD_AREA",
    "79,72": "BUILD_AREA",
    "79,73": "BUILD_AREA",
    "79,74": "BUILD_AREA",
    "79,75": "BUILD_AREA",
    "79,76": "BUILD_AREA",
    "79,77": "BUILD_AREA",
    "79,78": "BUILD_AREA"
  }
}
