{
  "id": "map_the_cross",
  "name": "The Cross",
  "width": 40,
  "height": 40,
  "readyToUse": true,
  "tiles": {
    "0,0": "SPAWN_POINT",
    "2,0": "SPAWN_POINT",
    "37,0": "SPAWN_POINT",
    "39,0": "SPAWN_POINT",
    "0,37": "SPAWN_POINT",
    "2,37": "SPAWN_POINT",
    "37,37": "SPAWN_POINT",
    "39,37": "SPAWN_POINT",
    "19,19": "TARGET",
    "20,19": "TARGET",
    "19,20": "TARGET",
    "20,20": "TARGET",
    "0,1": "PATH",
    "0,2": "PATH",
    "0,3": "PATH",
    "0,4": "PATH",
    "0,5": "PATH",
    "0,6": "PATH",
    "0,7": "PATH",
    "0,8": "PATH",
    "0,9": "PATH",
    "0,10": "PATH",
    "0,11": "PATH",
    "0,12": "PATH",
    "0,13": "PATH",
    "0,14": "PATH",
    "0,15": "PATH",
    "0,16": "PATH",
    "0,17": "PATH",
    "0,18": "PATH",
    "1,1": "PATH",
    "1,2": "PATH",
    "1,3": "PATH",
    "1,4": "PATH",
    "1,5": "PATH",
    "1,6": "PATH",
    "1,7": "PATH",
    "1,8": "PATH",
    "1,9": "PATH",
    "1,10": "PATH",
    "1,11": "PATH",
    "1,12": "PATH",
    "1,13": "PATH",
    "1,14": "PATH",
    "1,15": "PATH",
    "1,16": "PATH",
    "1,17": "PATH",
    "1,18": "PATH",
    "2,1": "PATH",
    "2,2": "PATH",
    "2,3": "PATH",
    "2,4": "PATH",
    "2,5": "PATH",
    "2,6": "PATH",
    "2,7": "PATH",
    "2,8": "PATH",
    "2,9": "PATH",
    "2,10": "PATH",
    "2,11": "PATH",
    "2,12": "PATH",
    "2,13": "PATH",
    "2,14": "PATH",
    "2,15": "PATH",
    "2,16": "PATH",
    "2,17": "PATH",
    "2,18": "PATH",
    "3,2": "PATH",
    "3,3": "PATH",
    "3,4": "PATH",
    "3,5": "PATH",
    "3,6": "PATH",
    "3,7": "PATH",
    "3,8": "PATH",
    "3,9": "PATH",
    "3,10": "PATH",
    "3,11": "PATH",
    "3,12": "PATH",
    "3,13": "PATH",
    "3,14": "PATH",
    "3,15": "PATH",
    "3,16": "PATH",
    "3,17": "PATH",
    "4,3": "PATH",
    "4,4": "PATH",
    "4,5": "PATH",
    "4,6": "PATH",
    "4,7": "PATH",
    "4,8": "PATH",
    "4,9": "PATH",
    "4,10": "PATH",
    "4,11": "PATH",
    "4,12": "PATH",
    "4,13": "PATH",
    "4,14": "PATH",
    "4,15": "PATH",
    "4,16": "PATH",
    "5,4": "PATH",
    "5,5": "PATH",
    "5,6": "PATH",
    "5,7": "PATH",
    "5,8": "PATH",
    "5,9": "PATH",
    "5,10": "PATH",
    "5,11": "PATH",
    "5,12": "PATH",
    "5,13": "PATH",
    "5,14": "PATH",
    "5,15": "PATH",
    "6,5": "PATH",
    "6,6": "PATH",
    "6,7": "PATH",
    "6,8": "PATH",
    "6,9": "PATH",
    "6,10": "PATH",
    "6,11": "PATH",
    "6,12": "PATH",
    "6,13": "PATH",
    "6,14": "PATH",
    "7,6": "PATH",
    "7,7": "PATH",
    "7,8": "PATH",
    "7,9": "PATH",
    "7,10": "PATH",
    "7,11": "PATH",
    "7,12": "PATH",
    "7,13": "PATH",
    "8,7": "PATH",
    "8,8": "PATH",
    "8,9": "PATH",
    "8,10": "PATH",
    "8,11": "PATH",
    "8,12": "PATH",
    "9,8": "PATH",
    "9,9": "PATH",
    "9,10": "PATH",
    "9,11": "PATH",
    "10,9": "PATH",
    "10,10": "PATH",
    "11,10": "PATH",
    "11,11": "PATH",
    "12,11": "PATH",
    "12,12": "PATH",
    "13,12": "PATH",
    "13,13": "PATH",
    "14,13": "PATH",
    "14,14": "PATH",
    "15,14": "PATH",
    "15,15": "PATH",
    "16,15": "PATH",
    "16,16": "PATH",
    "17,16": "PATH",
    "17,17": "PATH",
    "18,17": "PATH",
    "18,18": "PATH",
    "37,1": "PATH",
    "37,2": "PATH",
    "37,3": "PATH",
    "37,4": "PATH",
    "37,5": "PATH",
    "37,6": "PATH",
    "37,7": "PATH",
    "37,8": "PATH",
    "37,9": "PATH",
    "37,10": "PATH",
    "37,11": "PATH",
    "37,12": "PATH",
    "37,13": "PATH",
    "37,14": "PATH",
    "37,15": "PATH",
    "37,16": "PATH",
    "37,17": "PATH",
    "37,18": "PATH",
    "38,1": "PATH",
    "38,2": "PATH",
    "38,3": "PATH",
    "38,4": "PATH",
    "38,5": "PATH",
    "38,6": "PATH",
    "38,7": "PATH",
    "38,8": "PATH",
    "38,9": "PATH",
    "38,10": "PATH",
    "38,11": "PATH",
    "38,12": "PATH",
    "38,13": "PATH",
    "38,14": "PATH",
    "38,15": "PATH",
    "38,16": "PATH",
    "38,17": "PATH",
    "38,18": "PATH",
    "39,1": "PATH",
    "39,2": "PATH",
    "39,3": "PATH",
    "39,4": "PATH",
    "39,5": "PATH",
    "39,6": "PATH",
    "39,7": "PATH",
    "39,8": "PATH",
    "39,9": "PATH",
    "39,10": "PATH",
    "39,11": "PATH",
    "39,12": "PATH",
    "39,13": "PATH",
    "39,14": "PATH",
    "39,15": "PATH",
    "39,16": "PATH",
    "39,17": "PATH",
    "39,18": "PATH",
    "36,2": "PATH",
    "36,3": "PATH",
    "36,4": "PATH",
    "36,5": "PATH",
    "36,6": "PATH",
    "36,7": "PATH",
    "36,8": "PATH",
    "36,9": "PATH",
    "36,10": "PATH",
    "36,11": "PATH",
    "36,12": "PATH",
    "36,13": "PATH",
    "36,14": "PATH",
    "36,15": "PATH",
    "36,16": "PATH",
    "36,17": "PATH",
    "35,3": "PATH",
    "35,4": "PATH",
    "35,5": "PATH",
    "35,6": "PATH",
    "35,7": "PATH",
    "35,8": "PATH",
    "35,9": "PATH",
    "35,10": "PATH",
    "35,11": "PATH",
    "35,12": "PATH",
    "35,13": "PATH",
    "35,14": "PATH",
    "35,15": "PATH",
    "35,16": "PATH",
    "34,4": "PATH",
    "34,5": "PATH",
    "34,6": "PATH",
    "34,7": "PATH",
    "34,8": "PATH",
    "34,9": "PATH",
    "34,10": "PATH",
    "34,11": "PATH",
    "34,12": "PATH",
    "34,13": "PATH",
    "34,14": "PATH",
    "34,15": "PATH",
    "33,5": "PATH",
    "33,6": "PATH",
    "33,7": "PATH",
    "33,8": "PATH",
    "33,9": "PATH",
    "33,10": "PATH",
    "33,11": "PATH",
    "33,12": "PATH",
    "33,13": "PATH",
    "33,14": "PATH",
    "32,6": "PATH",
    "32,7": "PATH",
    "32,8": "PATH",
    "32,9": "PATH",
    "32,10": "PATH",
    "32,11": "PATH",
    "32,12": "PATH",
    "32,13": "PATH",
    "31,7": "PATH",
    "31,8": "PATH",
    "31,9": "PATH",
    "31,10": "PATH",
    "31,11": "PATH",
    "31,12": "PATH",
    "30,8": "PATH",
    "30,9": "PATH",
    "30,10": "PATH",
    "30,11": "PATH",
    "29,9": "PATH",
    "29,10": "PATH",
    "28,10": "PATH",
    "28,11": "PATH",
    "27,11": "PATH",
    "27,12": "PATH",
    "26,12": "PATH",
    "26,13": "PATH",
    "25,13": "PATH",
    "25,14": "PATH",
    "24,14": "PATH",
    "24,15": "PATH",
    "23,15": "PATH",
    "23,16": "PATH",
    "22,16": "PATH",
    "22,17": "PATH",
    "21,17": "PATH",
    "21,18": "PATH",
    "0,21": "PATH",
    "0,22": "PATH",
    "0,23": "PATH",
    "0,24": "PATH",
    "0,25": "PATH",
    "0,26": "PATH",
    "0,27": "PATH",
    "0,28": "PATH",
    "0,29": "PATH",
    "0,30": "PATH",
    "0,31": "PATH",
    "0,32": "PATH",
    "0,33": "PATH",
    "0,34": "PATH",
    "0,35": "PATH",
    "0,36": "PATH",
    "0,38": "PATH",
    "0,39": "PATH",
    "1,21": "PATH",
    "1,22": "PATH",
    "1,23": "PATH",
    "1,24": "PATH",
    "1,25": "PATH",
    "1,26": "PATH",
    "1,27": "PATH",
    "1,28": "PATH",
    "1,29": "PATH",
    "1,30": "PATH",
    "1,31": "PATH",
    "1,32": "PATH",
    "1,33": "PATH",
    "1,34": "PATH",
    "1,35": "PATH",
    "1,36": "PATH",
    "1,38": "PATH",
    "1,39": "PATH",
    "2,21": "PATH",
    "2,22": "PATH",
    "2,23": "PATH",
    "2,24": "PATH",
    "2,25": "PATH",
    "2,26": "PATH",
    "2,27": "PATH",
    "2,28": "PATH",
    "2,29": "PATH",
    "2,30": "PATH",
    "2,31": "PATH",
    "2,32": "PATH",
    "2,33": "PATH",
    "2,34": "PATH",
    "2,35": "PATH",
    "2,36": "PATH",
    "2,38": "PATH",
    "2,39": "PATH",
    "3,22": "PATH",
    "3,23": "PATH",
    "3,24": "PATH",
    "3,25": "PATH",
    "3,26": "PATH",
    "3,27": "PATH",
    "3,28": "PATH",
    "3,29": "PATH",
    "3,30": "PATH",
    "3,31": "PATH",
    "3,32": "PATH",
    "3,33": "PATH",
    "3,34": "PATH",
    "3,35": "PATH",
    "3,36": "PATH",
    "4,23": "PATH",
    "4,24": "PATH",
    "4,25": "PATH",
    "4,26": "PATH",
    "4,27": "PATH",
    "4,28": "PATH",
    "4,29": "PATH",
    "4,30": "PATH",
    "4,31": "PATH",
    "4,32": "PATH",
    "4,33": "PATH",
    "4,34": "PATH",
    "4,35": "PATH",
    "5,24": "PATH",
    "5,25": "PATH",
    "5,26": "PATH",
    "5,27": "PATH",
    "5,28": "PATH",
    "5,29": "PATH",
    "5,30": "PATH",
    "5,31": "PATH",
    "5,32": "PATH",
    "5,33": "PATH",
    "5,34": "PATH",
    "6,25": "PATH",
    "6,26": "PATH",
    "6,27": "PATH",
    "6,28": "PATH",
    "6,29": "PATH",
    "6,30": "PATH",
    "6,31": "PATH",
    "6,32": "PATH",
    "6,33": "PATH",
    "7,26": "PATH",
    "7,27": "PATH",
    "7,28": "PATH",
    "7,29": "PATH",
    "7,30": "PATH",
    "7,31": "PATH",
    "7,32": "PATH",
    "8,27": "PATH",
    "8,28": "PATH",
    "8,29": "PATH",
    "8,30": "PATH",
    "8,31": "PATH",
    "9,28": "PATH",
    "9,29": "PATH",
    "9,30": "PATH",
    "10,29": "PATH",
    "11,28": "PATH",
    "11,29": "PATH",
    "12,27": "PATH",
    "12,28": "PATH",
    "13,26": "PATH",
    "13,27": "PATH",
    "14,25": "PATH",
    "14,26": "PATH",
    "15,24": "PATH",
    "15,25": "PATH",
    "16,23": "PATH",
    "16,24": "PATH",
    "17,22": "PATH",
    "17,23": "PATH",
    "18,21": "PATH",
    "18,22": "PATH",
    "37,21": "PATH",
    "37,22": "PATH",
    "37,23": "PATH",
    "37,24": "PATH",
    "37,25": "PATH",
    "37,26": "PATH",
    "37,27": "PATH",
    "37,28": "PATH",
    "37,29": "PATH",
    "37,30": "PATH",
    "37,31": "PATH",
    "37,32": "PATH",
    "37,33": "PATH",
    "37,34": "PATH",
    "37,35": "PATH",
    "37,36": "PATH",
    "37,38": "PATH",
    "37,39": "PATH",
    "38,21": "PATH",
    "38,22": "PATH",
    "38,23": "PATH",
    "38,24": "PATH",
    "38,25": "PATH",
    "38,26": "PATH",
    "38,27": "PATH",
    "38,28": "PATH",
    "38,29": "PATH",
    "38,30": "PATH",
    "38,31": "PATH",
    "38,32": "PATH",
    "38,33": "PATH",
    "38,34": "PATH",
    "38,35": "PATH",
    "38,36": "PATH",
    "38,38": "PATH",
    "38,39": "PATH",
    "39,21": "PATH",
    "39,22": "PATH",
    "39,23": "PATH",
    "39,24": "PATH",
    "39,25": "PATH",
    "39,26": "PATH",
    "39,27": "PATH",
    "39,28": "PATH",
    "39,29": "PATH",
    "39,30": "PATH",
    "39,31": "PATH",
    "39,32": "PATH",
    "39,33": "PATH",
    "39,34": "PATH",
    "39,35": "PATH",
    "39,36": "PATH",
    "39,38": "PATH",
    "39,39": "PATH",
    "36,22": "PATH",
    "36,23": "PATH",
    "36,24": "PATH",
    "36,25": "PATH",
    "36,26": "PATH",
    "36,27": "PATH",
    "36,28": "PATH",
    "36,29": "PATH",
    "36,30": "PATH",
    "36,31": "PATH",
    "36,32": "PATH",
    "36,33": "PATH",
    "36,34": "PATH",
    "36,35": "PATH",
    "36,36": "PATH",
    "35,23": "PATH",
    "35,24": "PATH",
    "35,25": "PATH",
    "35,26": "PATH",
    "35,27": "PATH",
    "35,28": "PATH",
    "35,29": "PATH",
    "35,30": "PATH",
    "35,31": "PATH",
    "35,32": "PATH",
    "35,33": "PATH",
    "35,34": "PATH",
    "35,35": "PATH",
    "34,24": "PATH",
    "34,25": "PATH",
    "34,26": "PATH",
    "34,27": "PATH",
    "34,28": "PATH",
    "34,29": "PATH",
    "34,30": "PATH",
    "34,31": "PATH",
    "34,32": "PATH",
    "34,33": "PATH",
    "34,34": "PATH",
    "33,25": "PATH",
    "33,26": "PATH",
    "33,27": "PATH",
    "33,28": "PATH",
    "33,29": "PATH",
    "33,30": "PATH",
    "33,31": "PATH",
    "33,32": "PATH",
    "33,33": "PATH",
    "32,26": "PATH",
    "32,27": "PATH",
    "32,28": "PATH",
    "32,29": "PATH",
    "32,30": "PATH",
    "32,31": "PATH",
    "32,32": "PATH",
    "31,27": "PATH",
    "31,28": "PATH",
    "31,29": "PATH",
    "31,30": "PATH",
    "31,31": "PATH",
    "30,28": "PATH",
    "30,29": "PATH",
    "30,30": "PATH",
    "29,29": "PATH",
    "28,28": "PATH",
    "28,29": "PATH",
    "27,27": "PATH",
    "27,28": "PATH",
    "26,26": "PATH",
    "26,27": "PATH",
    "25,25": "PATH",
    "25,26": "PATH",
    "24,24": "PATH",
    "24,25": "PATH",
    "23,23": "PATH",
    "23,24": "PATH",
    "22,22": "PATH",
    "22,23": "PATH",
    "21,21": "PATH",
    "21,22": "PATH",
    "10,19": "BUILD_AREA",
    "11,18": "BUILD_AREA",
    "11,19": "BUILD_AREA",
    "12,18": "BUILD_AREA",
    "12,19": "BUILD_AREA",
    "13,18": "BUILD_AREA",
    "13,19": "BUILD_AREA",
    "14,18": "BUILD_AREA",
    "14,19": "BUILD_AREA",
    "15,18": "BUILD_AREA",
    "15,19": "BUILD_AREA",
    "16,18": "BUILD_AREA",
    "16,19": "BUILD_AREA",
    "17,18": "BUILD_AREA",
    "17,19": "BUILD_AREA",
    "18,19": "BUILD_AREA",
    "18,20": "BUILD_AREA",
    "19,18": "BUILD_AREA",
    "19,21": "BUILD_AREA",
    "20,18": "BUILD_AREA",
    "20,21": "BUILD_AREA",
    "21,19": "BUILD_AREA",
    "21,20": "BUILD_AREA",
    "22,19": "BUILD_AREA",
    "22,20": "BUILD_AREA",
    "22,21": "BUILD_AREA",
    "23,19": "BUILD_AREA",
    "23,20": "BUILD_AREA",
    "23,21": "BUILD_AREA",
    "23,22": "BUILD_AREA",
    "24,20": "BUILD_AREA",
    "24,21": "BUILD_AREA",
    "24,22": "BUILD_AREA",
    "24,23": "BUILD_AREA",
    "25,20": "BUILD_AREA",
    "25,21": "BUILD_AREA",
    "25,22": "BUILD_AREA",
    "25,23": "BUILD_AREA",
    "26,20": "BUILD_AREA",
    "26,21": "BUILD_AREA",
    "26,22": "BUILD_AREA",
    "26,23": "BUILD_AREA",
    "26,24": "BUILD_AREA",
    "26,25": "BUILD_AREA",
    "27,21": "BUILD_AREA",
    "27,22": "BUILD_AREA",
    "27,23": "BUILD_AREA",
    "27,24": "BUILD_AREA",
    "27,25": "BUILD_AREA",
    "27,26": "BUILD_AREA",
    "28,21": "BUILD_AREA",
    "28,22": "BUILD_AREA",
    "28,23": "BUILD_AREA",
    "28,24": "BUILD_AREA",
    "28,25": "BUILD_AREA",
    "28,26": "BUILD_AREA",
    "28,27": "BUILD_AREA",
    "29,20": "BUILD_AREA",
    "10,20": "BUILD_AREA",
    "11,20": "BUILD_AREA",
    "11,21": "BUILD_AREA",
    "12,20": "BUILD_AREA",
    "12,21": "BUILD_AREA",
    "13,20": "BUILD_AREA",
    "13,21": "BUILD_AREA",
    "14,20": "BUILD_AREA",
    "14,21": "BUILD_AREA",
    "15,20": "BUILD_AREA",
    "15,21": "BUILD_AREA",
    "16,20": "BUILD_AREA",
    "16,21": "BUILD_AREA",
    "16,22": "BUILD_AREA",
    "17,20": "BUILD_AREA",
    "17,21": "BUILD_AREA",
    "18,16": "BUILD_AREA",
    "18,15": "BUILD_AREA",
    "18,14": "BUILD_AREA",
    "18,13": "BUILD_AREA",
    "18,12": "BUILD_AREA",
    "18,11": "BUILD_AREA",
    "18,10": "BUILD_AREA",
    "18,9": "BUILD_AREA",
    "18,8": "BUILD_AREA",
    "18,7": "BUILD_AREA",
    "18,6": "BUILD_AREA",
    "18,5": "BUILD_AREA",
    "18,4": "BUILD_AREA",
    "18,3": "BUILD_AREA",
    "17,15": "BUILD_AREA",
    "17,14": "BUILD_AREA",
    "17,13": "BUILD_AREA",
    "17,12": "BUILD_AREA",
    "17,11": "BUILD_AREA",
    "17,10": "BUILD_AREA",
    "17,9": "BUILD_AREA",
    "17,8": "BUILD_AREA",
    "17,7": "BUILD_AREA",
    "17,6": "BUILD_AREA",
    "17,5": "BUILD_AREA",
    "16,14": "BUILD_AREA",
    "16,13": "BUILD_AREA",
    "16,12": "BUILD_AREA",
    "16,11": "BUILD_AREA",
    "16,10": "BUILD_AREA",
    "16,9": "BUILD_AREA",
    "16,8": "BUILD_AREA",
    "16,7": "BUILD_AREA",
    "16,6": "BUILD_AREA",
    "15,13": "BUILD_AREA",
    "15,12": "BUILD_AREA",
    "15,11": "BUILD_AREA",
    "15,10": "BUILD_AREA",
    "15,9": "BUILD_AREA",
    "15,8": "BUILD_AREA",
    "15,7": "BUILD_AREA",
    "15,6": "BUILD_AREA",
    "14,12": "BUILD_AREA",
    "14,11": "BUILD_AREA",
    "14,10": "BUILD_AREA",
    "14,9": "BUILD_AREA",
    "14,8": "BUILD_AREA",
    "14,7": "BUILD_AREA",
    "13,11": "BUILD_AREA",
    "13,10": "BUILD_AREA",
    "13,9": "BUILD_AREA",
    "13,8": "BUILD_AREA",
    "13,7": "BUILD_AREA",
    "12,10": "BUILD_AREA",
    "12,9": "BUILD_AREA",
    "12,8": "BUILD_AREA",
    "11,9": "BUILD_AREA",
    "21,24": "BUILD_AREA",
    "21,25": "BUILD_AREA",
    "21,26": "BUILD_AREA",
    "21,27": "BUILD_AREA",
    "21,28": "BUILD_AREA",
    "21,29": "BUILD_AREA",
    "21,30": "BUILD_AREA",
    "21,31": "BUILD_AREA",
    "21,32": "BUILD_AREA",
    "21,33": "BUILD_AREA",
    "21,34": "BUILD_AREA",
    "21,35": "BUILD_AREA",
    "21,36": "BUILD_AREA",
    "22,24": "BUILD_AREA",
    "22,25": "BUILD_AREA",
    "22,26": "BUILD_AREA",
    "22,27": "BUILD_AREA",
    "22,28": "BUILD_AREA",
    "22,29": "BUILD_AREA",
    "22,30": "BUILD_AREA",
    "22,31": "BUILD_AREA",
    "22,32": "BUILD_AREA",
    "22,33": "BUILD_AREA",
    "22,34": "BUILD_AREA",
    "22,35": "BUILD_AREA",
    "23,25": "BUILD_AREA",
    "23,26": "BUILD_AREA",
    "23,27": "BUILD_AREA",
    "23,28": "BUILD_AREA",
    "23,29": "BUILD_AREA",
    "23,30": "BUILD_AREA",
    "23,31": "BUILD_AREA",
    "23,32": "BUILD_AREA",
    "23,33": "BUILD_AREA",
    "23,34": "BUILD_AREA",
    "24,26": "BUILD_AREA",
    "24,27": "BUILD_AREA",
    "24,28": "BUILD_AREA",
    "24,29": "BUILD_AREA",
    "24,30": "BUILD_AREA",
    "24,31": "BUILD_AREA",
    "24,32": "BUILD_AREA",
    "24,33": "BUILD_AREA",
    "25,27": "BUILD_AREA",
    "25,28": "BUILD_AREA",
    "25,29": "BUILD_AREA",
    "25,30": "BUILD_AREA",
    "25,31": "BUILD_AREA",
    "25,32": "BUILD_AREA",
    "26,28": "BUILD_AREA",
    "26,29": "BUILD_AREA",
    "26,30": "BUILD_AREA",
    "26,31": "BUILD_AREA",
    "27,29": "BUILD_AREA",
    "27,30": "BUILD_AREA",
    "28,30": "BUILD_AREA",
    "19,3": "BUILD_AREA",
    "19,4": "BUILD_AREA",
    "19,5": "BUILD_AREA",
    "19,6": "BUILD_AREA",
    "19,7": "BUILD_AREA",
    "19,8": "BUILD_AREA",
    "19,9": "BUILD_AREA",
    "19,10": "BUILD_AREA",
    "19,11": "BUILD_AREA",
    "19,12": "BUILD_AREA",
    "19,13": "BUILD_AREA",
    "19,14": "BUILD_AREA",
    "19,15": "BUILD_AREA",
    "19,16": "BUILD_AREA",
    "20,3": "BUILD_AREA",
    "20,4": "BUILD_AREA",
    "20,5": "BUILD_AREA",
    "20,6": "BUILD_AREA",
    "20,7": "BUILD_AREA",
    "20,8": "BUILD_AREA",
    "20,9": "BUILD_AREA",
    "20,10": "BUILD_AREA",
    "20,11": "BUILD_AREA",
    "20,12": "BUILD_AREA",
    "20,13": "BUILD_AREA",
    "20,14": "BUILD_AREA",
    "20,15": "BUILD_AREA",
    "20,16": "BUILD_AREA",
    "21,3": "BUILD_AREA",
    "21,4": "BUILD_AREA",
    "21,5": "BUILD_AREA",
    "21,6": "BUILD_AREA",
    "21,7": "BUILD_AREA",
    "21,8": "BUILD_AREA",
    "21,9": "BUILD_AREA",
    "21,10": "BUILD_AREA",
    "21,11": "BUILD_AREA",
    "21,12": "BUILD_AREA",
    "21,13": "BUILD_AREA",
    "21,14": "BUILD_AREA",
    "21,15": "BUILD_AREA",
    "21,16": "BUILD_AREA",
    "22,4": "BUILD_AREA",
    "22,5": "BUILD_AREA",
    "22,6": "BUILD_AREA",
    "22,7": "BUILD_AREA",
    "22,8": "BUILD_AREA",
    "22,9": "BUILD_AREA",
    "22,10": "BUILD_AREA",
    "22,11": "BUILD_AREA",
    "22,12": "BUILD_AREA",
    "22,13": "BUILD_AREA",
    "22,14": "BUILD_AREA",
    "22,15": "BUILD_AREA",
    "23,5": "BUILD_AREA",
    "23,6": "BUILD_AREA",
    "23,7": "BUILD_AREA",
    "23,8": "BUILD_AREA",
    "23,9": "BUILD_AREA",
    "23,10": "BUILD_AREA",
    "23,11": "BUILD_AREA",
    "23,12": "BUILD_AREA",
    "23,13": "BUILD_AREA",
    "23,14": "BUILD_AREA",
    "24,6": "BUILD_AREA",
    "24,7": "BUILD_AREA",
    "24,8": "BUILD_AREA",
    "24,9": "BUILD_AREA",
    "24,10": "BUILD_AREA",
    "24,11": "BUILD_AREA",
    "24,12": "BUILD_AREA",
    "24,13": "BUILD_AREA",
    "25,7": "BUILD_AREA",
    "25,8": "BUILD_AREA",
    "25,9": "BUILD_AREA",
    "25,10": "BUILD_AREA",
    "25,11": "BUILD_AREA",
    "25,12": "BUILD_AREA",
    "26,8": "BUILD_AREA",
    "26,9": "BUILD_AREA",
    "26,10": "BUILD_AREA",
    "26,11": "BUILD_AREA",
    "27,9": "BUILD_AREA",
    "27,10": "BUILD_AREA",
    "28,9": "BUILD_AREA"
  }
}
